Workbook

Sheet Info recyclage
D5: Prix moyen par tonne traitée en 2020 | E5: Remise contractuelle par tonne | F5: Déchets reçus (tonnes) | G5: Total des ventes | H5: Total des remises (incluses dans le CMV) | I5: Coûts variables par tonne | J5: Total des coûts variables
C7: Carton ondulé | D7: 119 | E7: 50 | F7: 59550 | G7: =F7*D7 -> 7086450 | H7: =F7*E7 -> 2977500 | I7: 15 | J7: =F7*I7 -> 893250
C8: Papiers résidentiels mélangés | D8: 1.9 | E8: 1 | F8: 101000 | G8: =F8*D8 -> 191900 | H8: =F8*E8 -> 101000 | I8: 2.1 | J8: =F8*I8 -> 212100
C9: Verre | D9: 0.5 | E9: 1 | F9: 39700 | G9: =F9*D9 -> 19850 | H9: =F9*E9 -> 39700 | I9: 1.92 | J9: =F9*I9 -> 76224
G10: =SUM(G7:G9) -> 7298200 | H10: =SUM(H7:H9) -> 3118200 | J10: =SUM(J7:J9) -> 1181574
H12: Total des coûts variables :
H13: Coût des marchandises vendues, selon les ÉF | J13: ='États financiers - Analyse'!B20*1000 -> 4300000
H14: Moins les remises | J14: =-H10 -> -3118200
H15: Total | I15: Remarque | J15: =SUM(J13:J14) -> 1181800
C17: Remarque : Le total des coûts variables présente de légères différences en raison de l’arrondissement.

Sheet ANN III – Info sectorielle
C3: Collecte | D3: Transfert | E3: Enfouissement | F3: Recyclage | G3: Total
C4: (en milliers de dollars canadiens)
B6: Produits | C6: 48400 | D6: 8200 | E6: 17300 | F6: 7300 | G6: =SUM(C6:F6) -> 81200
B8: Charges
B9: Main-d’œuvre et avantages sociaux | C9: 8670 | D9: 1270 | E9: 2100 | F9: 1700 | G9: =SUM(C9:F9) -> 13740
B10: Coût des marchandises vendues* | C10: 0 | D10: 0 | E10: 0 | F10: 4300 | G10: =SUM(C10:F10) -> 4300
B11: Achats – carburant et autres | C11: 16000 | D11: 1440 | E11: 2280 | F11: 0 | G11: =SUM(C11:F11) -> 19720
B12: Amortissement | C12: 3800 | D12: 680 | E12: 3865 | F12: 365 | G12: =SUM(C12:F12) -> 8710
B13: Autres coûts d’exploitation | C13: 12100 | D13: 3007 | E13: 3840 | F13: 815 | G13: =SUM(C13:F13) -> 19762
B14: Frais de vente et d’administration | C14: 0 | D14: 0 | E14: 0 | F14: 0 | G14: 8300
C15: =SUM(C9:C14) -> 40570 | D15: =SUM(D9:D14) -> 6397 | E15: =SUM(E9:E14) -> 12085 | F15: =SUM(F9:F14) -> 7180 | G15: =SUM(G9:G14) -> 74532
B16: Bénéfice d’exploitation | C16: =C6-C15 -> 7830 | D16: =D6-D15 -> 1803 | E16: =E6-E15 -> 5215 | F16: =F6-F15 -> 120 | G16: =G6-G15 -> 6668
B18: Marge d’exploitation | C18: =C16/C6 -> 0.16177686 | D18: =D16/D6 -> 0.21987805 | E18: =E16/E6 -> 0.30144509 | F18: =F16/F6 -> 0.016438356 | G18: =G16/G6 -> 0.082118227
B20: Intérêts débiteurs | G20: ='États financiers - Analyse'!B29+'États financiers - Analyse'!B30+'États financiers - Analyse'!B31 -> -3584
B21: Charge de désactualisation | G21: =-'États financiers - Analyse'!B23 -> -140
B22: Bénéfice net avant impôts | G22: =G16+G20+G21 -> 2944
B23: Impôts sur les bénéfices | G23: ='États financiers - Analyse'!B33 -> -780
B24: Bénéfice net | G24: =SUM(G22:G23) -> 2164 | H24: =G24/G6 -> 0.026650246
B26: * Inclut 100 $ liés aux coûts du carburant.

Sheet ANN IV – Données réf. sector.
D4: Données de référence
B5: Industrie de la gestion des déchets
B7: Charges en pourcentage du total des produits
B8: Main-d’œuvre et avantages sociaux | D8: 0.166
B9: Carburant et autres achats | D9: 0.22
B10: Amortissement | D10: 0.072
B11: Autres coûts d’exploitation | D11: 0.262
B12: Frais de vente et d’administration | D12: 0.1
B14: Marge du bénéfice d’exploitation | D14: 0.1
B15: Rendement de l’actif | D15: 0.09
B16: Rendement des capitaux propres | D16: 0.08
B18: Ratio de liquidité générale | D18: 1.5
B19: Délai de recouvrement des créances | D19: 45
B20: Ratio emprunts/capitaux propres | D20: 2.6
B21: Dette à long terme/BAIIA | D21: 3.1
B23: Secteur du recyclage
B25: Charges en pourcentage du total des produits
B26: Main-d’œuvre et avantages sociaux | D26: 0.212
B27: Coût des marchandises vendues | D27: 0.541
B28: Amortissement | D28: 0.059
B29: Autres coûts d’exploitation | D29: 0.125
B31: Marge du bénéfice d’exploitation | D31: 0.043

Sheet États financiers - Analyse
A3: Waste Disposal Inc.
A4: État des résultats
A5: pour les exercices clos les 31 décembre
A6: (en milliers de dollars canadiens)
B8: PROJET | D8: AUDITÉ | F8: AUDITÉ | H8: Analyse horizontale
B9: 2020 | D9: 2019 | F9: 2018 | H9: 2019-2020 | I9: 2018-2019
B10: $ | D10: $ | F10: $
J11: Croissances ventes industrie | K11: Élément améliorant la rentabilité | L11: Élément détériorant la rentabilité
A12: Collecte | B12: ='ANN III – Info sectorielle'!C6 -> 48400 | C12: =B12/$B$16 -> 0.59605911 | D12: 47500 | E12: =D12/$D$16 -> 0.58823529 | F12: 46700 | G12: =F12/$F$16 -> 0.58222167 | H12: =(B12-D12)/D12 -> 0.018947368 | I12: =(D12-F12)/F12 -> 0.017130621 | J12: 0.02
A13: Transfert | B13: ='ANN III – Info sectorielle'!D6 -> 8200 | C13: =B13/$B$16 -> 0.10098522 | D13: 8050 | E13: =D13/$D$16 -> 0.099690402 | F13: 7910 | G13: =F13/$F$16 -> 0.098616133 | H13: =(B13-D13)/D13 -> 0.01863354 | I13: =(D13-F13)/F13 -> 0.017699115 | J13: 0.02
A14: Enfouissement | B14: ='ANN III – Info sectorielle'!E6 -> 17300 | C14: =B14/$B$16 -> 0.21305419 | D14: 16700 | E14: =D14/$D$16 -> 0.20681115 | F14: 16400 | G14: =F14/$F$16 -> 0.20446328 | H14: =(B14-D14)/D14 -> 0.035928144 | I14: =(D14-F14)/F14 -> 0.018292683 | J14: 0.02
A15: Recyclage | B15: ='ANN III – Info sectorielle'!F6 -> 7300 | C15: =B15/$B$16 -> 0.089901478 | D15: 8500 | E15: =D15/$D$16 -> 0.10526316 | F15: 9200 | G15: =F15/$F$16 -> 0.11469892 | H15: =(B15-D15)/D15 -> -0.14117647 | I15: =(D15-F15)/F15 -> -0.076086957 | J15: -0.02 | L15: (20) diminution des prix pour les matières recyclées
B16: =SUM(B12:B15) -> 81200 | C16: =B16/$B$16 -> 1 | D16: =SUM(D12:D15) -> 80750 | E16: =D16/$D$16 -> 1 | F16: =SUM(F12:F15) -> 80210 | G16: =F16/$F$16 -> 1 | H16: =(B16-D16)/D16 -> 0.0055727554 | I16: =(D16-F16)/F16 -> 0.0067323276 | K16: (3) contrat long terme/relation client | L16: (13) offre de service limitée (16) difficulté à acquérir de nouveaux clients
A18: Charges | J18: charge en % des produits - industrie
A19: Main-d’œuvre et avantages sociaux | B19: ='ANN III – Info sectorielle'!G9 -> 13740 | C19: =B19/$B$16 -> 0.16921182 | D19: 12200 | E19: =D19/$D$16 -> 0.15108359 | F19: 11640 | G19: =F19/$F$16 -> 0.14511906 | H19: =(B19-D19)/D19 -> 0.12622951 | I19: =(D19-F19)/F19 -> 0.048109966 | J19: 0.166 | L19: (4) stabilité de la MOD
A20: Coût des marchandises vendues – recyclage | B20: ='ANN III – Info sectorielle'!G10 -> 4300 | C20: =B20/$B$16 -> 0.052955665 | D20: 4100 | E20: =D20/$D$16 -> 0.050773994 | F20: 4000 | G20: =F20/$F$16 -> 0.049869094 | H20: =(B20-D20)/D20 -> 0.048780488 | I20: =(D20-F20)/F20 -> 0.025
A21: Carburant et autres achats – exclusion faite du recyclage | B21: ='ANN III – Info sectorielle'!G11 -> 19720 | C21: =B21/$B$16 -> 0.24285714 | D21: 19700 | E21: =D21/$D$16 -> 0.24396285 | F21: 19700 | G21: =F21/$F$16 -> 0.24560529 | H21: =(B21-D21)/D21 -> 0.0010152284 | I21: =(D21-F21)/F21 -> 0 | J21: 0.22 | K21: (1) installations à proximité, (10) logiciel d'optimisation | L21: (19) 5% des camions sont au biogaz
A22: Amortissement | B22: ='ANN III – Info sectorielle'!G12 -> 8710 | C22: =B22/$B$16 -> 0.10726601 | D22: 7650 | E22: =D22/$D$16 -> 0.094736842 | F22: 7300 | G22: =F22/$F$16 -> 0.091011096 | H22: =(B22-D22)/D22 -> 0.13856209 | I22: =(D22-F22)/F22 -> 0.047945205 | J22: =Ratios!F14 -> 0.072 | L22: (5) propriétaire de tous ses actifs
A23: Charge de désactualisation sur l’obligation liée à la remise en état des sites d’enfouissement | B23: 140 | C23: =B23/$B$16 -> 0.0017241379 | D23: 135 | E23: =D23/$D$16 -> 0.0016718266 | F23: 120 | G23: =F23/$F$16 -> 0.0014960728 | H23: =(B23-D23)/D23 -> 0.037037037 | I23: =(D23-F23)/F23 -> 0.125
A24: Autres coûts d’exploitation | B24: ='ANN III – Info sectorielle'!$G$13 -> 19762 | C24: =B24/$B$16 -> 0.24337438 | D24: 18485 | E24: =D24/$D$16 -> 0.22891641 | F24: 17740 | G24: =F24/$F$16 -> 0.22116943 | H24: =(B24-D24)/D24 -> 0.06908304 | I24: =(D24-F24)/F24 -> 0.04199549 | J24: 0.262 | K24: (5) propriétaire de tous ses actifs | L24: (11) retard technologique
A25: Frais de vente et d’administration | B25: ='ANN III – Info sectorielle'!G14 -> 8300 | C25: =B25/$B$16 -> 0.10221675 | D25: 8050 | E25: =D25/$D$16 -> 0.099690402 | F25: 7920 | G25: =F25/$F$16 -> 0.098740805 | H25: =(B25-D25)/D25 -> 0.031055901 | I25: =(D25-F25)/F25 -> 0.016414141 | J25: 0.1
A26: Total des charges | B26: =SUM(B19:B25) -> 74672 | C26: =B26/$B$16 -> 0.91960591 | D26: =SUM(D19:D25) -> 70320 | E26: =D26/$D$16 -> 0.87083591 | F26: =SUM(F19:F25) -> 68420 | G26: =F26/$F$16 -> 0.85301085 | H26: =(B26-D26)/D26 -> 0.06188851 | I26: =(D26-F26)/F26 -> 0.027769658 | L26: (18) plus petite taille - moins d'économies d'échelle
A28: Bénéfice d’exploitation | B28: =B16-B26 -> 6528 | C28: =B28/$B$16 -> 0.080394089 | D28: =D16-D26 -> 10430 | E28: =D28/$D$16 -> 0.12916409 | F28: =F16-F26 -> 11790 | G28: =F28/$F$16 -> 0.14698915 | H28: =(B28-D28)/D28 -> -0.37411314 | I28: =(D28-F28)/F28 -> -0.11535199
A29: Intérêts débiteurs – ligne de crédit | B29: -22 | C29: =B29/$B$16 -> -0.00027093596 | D29: 0 | E29: =D29/$D$16 -> 0 | F29: 0 | G29: =F29/$F$16 -> 0
A30: Intérêts débiteurs – emprunt auprès de REC | B30: -78 | C30: =B30/$B$16 -> -0.00096059113 | D30: -560 | E30: =D30/$D$16 -> -0.0069349845 | F30: -560 | G30: =F30/$F$16 -> -0.0069816731 | H30: =(B30-D30)/D30 -> -0.86071429 | I30: =(D30-F30)/F30 -> 0
A31: Intérêts débiteurs – emprunt auprès de GBI | B31: =-ROUND((B77+B80)*0.065,0) -> -3484 | C31: =B31/$B$16 -> -0.042906404 | D31: =-ROUND((D77+D80)*0.065,0) -> -3744 | E31: =D31/$D$16 -> -0.046365325 | F31: =-ROUND((F77+F80)*0.065,0) -> -4004 | G31: =F31/$F$16 -> -0.049918963 | H31: =(B31-D31)/D31 -> -0.069444444 | I31: =(D31-F31)/F31 -> -0.064935065
A32: Bénéfice avant impôts | B32: =B28+B29+B30+B31 -> 2944 | C32: =B32/$B$16 -> 0.036256158 | D32: =D28+D30+D31 -> 6126 | E32: =D32/$D$16 -> 0.075863777 | F32: =F28+F30+F31 -> 7226 | G32: =F32/$F$16 -> 0.090088518 | H32: =(B32-D32)/D32 -> -0.5194254 | I32: =(D32-F32)/F32 -> -0.15222807
A33: Impôts sur les bénéfices | B33: =-ROUND(B32*0.265,0) -> -780 | C33: =B33/$B$16 -> -0.0096059113 | D33: =-ROUND(D32*0.265,0) -> -1623 | E33: =D33/$D$16 -> -0.020099071 | F33: =-ROUND(F32*0.265,0) -> -1915 | G33: =F33/$F$16 -> -0.023874829 | H33: =(B33-D33)/D33 -> -0.5194085 | I33: =(D33-F33)/F33 -> -0.15248042
A34: Bénéfice net | B34: =B32+B33 -> 2164 | C34: =B34/$B$16 -> 0.026650246 | D34: =D32+D33 -> 4503 | E34: =D34/$D$16 -> 0.055764706 | F34: =F32+F33 -> 5311 | G34: =F34/$F$16 -> 0.066213689 | H34: =(B34-D34)/D34 -> -0.51943149 | I34: =(D34-F34)/F34 -> -0.15213707
A38: Waste Disposal Inc.
A39: État des bénéfices non répartis
A40: pour les exercices clos les 31 décembre
A41: (en milliers de dollars canadiens)
B42: PROJET | D42: AUDITÉ | F42: AUDITÉ
B43: 2020 | D43: 2019 | F43: 2018
B44: $ | D44: $ | F44: $
A45: Solde à l’ouverture de l’exercice | B45: =D48 -> 11952 | D45: =F48 -> 7449 | F45: 8092
A46: Bénéfice net | B46: =B34 -> 2164 | D46: =D34 -> 4503 | F46: =F34 -> 5311
A47: Dividendes | B47: 0 | D47: 0 | F47: -5954
A48: Solde à la clôture de l’exercice | B48: =SUM(B45:B47) -> 14116 | D48: =SUM(D45:D47) -> 11952 | F48: =SUM(F45:F47) -> 7449
A53: Waste Disposal Inc.
A54: Bilan
A55: aux 31 décembre
A56: (en milliers de dollars canadiens)
B57: PROJET | D57: AUDITÉ | F57: AUDITÉ
B58: 2020 | D58: 2019 | F58: 2018
B59: $ | D59: $ | F59: $
A60: Actif
A61: Actif à court terme
A62: Trésorerie et équivalents de trésorerie | B62: 120 | C62: =B62/$B$68 -> 0.0012525312 | D62: 350 | E62: =D62/$D$68 -> 0.0037262187 | F62: 680 | G62: =F62/$F$68 -> 0.0073228516 | H62: =(B62-D62)/D62 -> -0.65714286 | I62: =(D62-F62)/F62 -> -0.48529412
A63: Créances clients | B63: 10100 | C63: =B63/$B$68 -> 0.10542137 | D63: 9200 | E63: =D63/$D$68 -> 0.097946321 | F63: 8790 | G63: =F63/$F$68 -> 0.094658626 | H63: =(B63-D63)/D63 -> 0.097826087 | I63: =(D63-F63)/F63 -> 0.046643914
A64: Frais payés d’avance | B64: 1280 | C64: =B64/$B$68 -> 0.013360332 | D64: 1250 | E64: =D64/$D$68 -> 0.013307924 | F64: 1190 | G64: =F64/$F$68 -> 0.01281499 | H64: =(B64-D64)/D64 -> 0.024 | I64: =(D64-F64)/F64 -> 0.050420168
A65: Total de l’actif à court terme | B65: =SUM(B62:B64) -> 11500 | C65: =B65/$B$68 -> 0.12003424 | D65: =SUM(D62:D64) -> 10800 | E65: =D65/$D$68 -> 0.11498046 | F65: =SUM(F62:F64) -> 10660 | G65: =F65/$F$68 -> 0.11479647 | H65: =(B65-D65)/D65 -> 0.064814815 | I65: =(D65-F65)/F65 -> 0.013133208
G66: =F66/$F$68 -> 0
A67: Immobilisations corporelles – montant net (Note 1) | B67: =B96 -> 84306 | C67: =B67/$B$68 -> 0.87996576 | D67: =D96 -> 83129 | E67: =D67/$D$68 -> 0.88501954 | F67: =F96 -> 82200 | G67: =F67/$F$68 -> 0.88520353 | H67: =(B67-D67)/D67 -> 0.014158717 | I67: =(D67-F67)/F67 -> 0.011301703
A68: Total de l’actif | B68: =SUM(B65:B67) -> 95806 | C68: =B68/$B$68 -> 1 | D68: =SUM(D65:D67) -> 93929 | E68: =D68/$D$68 -> 1 | F68: =SUM(F65:F67) -> 92860 | G68: =F68/$F$68 -> 1 | H68: =(B68-D68)/D68 -> 0.019983179 | I68: =(D68-F68)/F68 -> 0.011511953
A70: Passif
A71: Passif à court terme
A72: Ligne de crédit | B72: 1300 | C72: =B72/$B$89 -> 0.013569088 | D72: 0 | E72: =D72/$D$89 -> 0 | F72: 0 | G72: =F72/$F$89 -> 0
A73: Fournisseurs et charges à payer | B73: 5828 | C73: =B73/$B$89 -> 0.060831263 | D73: 5255 | E73: =D73/$D$89 -> 0.055946513 | F73: 4944 | G73: =F73/$F$89 -> 0.053241439 | H73: =(B73-D73)/D73 -> 0.10903901 | I73: =(D73-F73)/F73 -> 0.062904531
A74: Impôts à payer | B74: 250 | C74: =B74/$B$89 -> 0.0026094399 | D74: 650 | E74: =D74/$D$89 -> 0.0069201205 | F74: 700 | G74: =F74/$F$89 -> 0.0075382296 | H74: =(B74-D74)/D74 -> -0.61538462 | I74: =(D74-F74)/F74 -> -0.071428571
A75: Produits reportés | B75: 2680 | C75: =B75/$B$89 -> 0.027973196 | D75: 2580 | E75: =D75/$D$89 -> 0.027467555 | F75: 2410 | G75: =F75/$F$89 -> 0.025953048 | H75: =(B75-D75)/D75 -> 0.03875969 | I75: =(D75-F75)/F75 -> 0.070539419
A76: Tranche à court terme – REC | B76: 0 | C76: =B76/$B$89 -> 0 | D76: 8000 | E76: =D76/$D$89 -> 0.085170714 | F76: 0 | G76: =F76/$F$89 -> 0
A77: Tranche à court terme – GBI | B77: 4000 | C77: =B77/$B$89 -> 0.041751039 | D77: 4000 | E77: =D77/$D$89 -> 0.042585357 | F77: 4000 | G77: =F77/$F$89 -> 0.043075598 | H77: =(B77-D77)/D77 -> 0 | I77: =(D77-F77)/F77 -> 0
A78: Total du passif à court terme | B78: =SUM(B72:B77) -> 14058 | C78: =B78/$B$89 -> 0.14673403 | D78: =SUM(D72:D77) -> 20485 | E78: =D78/$D$89 -> 0.21809026 | F78: =SUM(F72:F77) -> 12054 | G78: =F78/$F$89 -> 0.12980831 | H78: =(B78-D78)/D78 -> -0.31374176 | I78: =(D78-F78)/F78 -> 0.69943587
A80: Dette à long terme – GBI | B80: 49600 | C80: =B80/$B$89 -> 0.51771288 | D80: 53600 | E80: =D80/$D$89 -> 0.57064378 | F80: 57600 | G80: =F80/$F$89 -> 0.62028861 | H80: =(B80-D80)/D80 -> -0.074626866 | I80: =(D80-F80)/F80 -> -0.069444444
A81: Dette à long terme – REC | B81: 0 | D81: 0 | E81: =D81/$D$89 -> 0 | F81: 8000 | G81: =F81/$F$89 -> 0.086151195
A82: Obligations liées à la mise hors service d’immobilisations – sites d’enfouissement (Note 2) | B82: 7032 | C82: =B82/$B$89 -> 0.073398326 | D82: 6892 | E82: =D82/$D$89 -> 0.07337457 | F82: 6757 | G82: =F82/$F$89 -> 0.072765453 | H82: =(B82-D82)/D82 -> 0.020313407 | I82: =(D82-F82)/F82 -> 0.019979281
A83: Total du passif | B83: =SUM(B78:B82) -> 70690 | C83: =B83/$B$89 -> 0.73784523 | D83: =SUM(D78:D82) -> 80977 | E83: =D83/$D$89 -> 0.86210861 | F83: =SUM(F78:F82) -> 84411 | G83: =F83/$F$89 -> 0.90901357 | H83: =(B83-D83)/D83 -> -0.12703607 | I83: =(D83-F83)/F83 -> -0.040681902
A85: Capitaux propres
A86: Capital-actions (1 000 000 d’actions en circulation) | B86: 11000 | C86: =B86/$B$89 -> 0.11481536 | D86: 1000 | E86: =D86/$D$89 -> 0.010646339 | F86: 1000 | G86: =F86/$F$89 -> 0.010768899 | H86: =(B86-D86)/D86 -> 10 | I86: =(D86-F86)/F86 -> 0
A87: Bénéfices non répartis | B87: =B48 -> 14116 | C87: =B87/$B$89 -> 0.14733942 | D87: =D48 -> 11952 | E87: =D87/$D$89 -> 0.12724505 | F87: =F48 -> 7449 | G87: =F87/$F$89 -> 0.080217532 | H87: =(B87-D87)/D87 -> 0.18105756 | I87: =(D87-F87)/F87 -> 0.60451067
A88: Total des capitaux propres | B88: =SUM(B86:B87) -> 25116 | C88: =B88/$B$89 -> 0.26215477 | D88: =SUM(D86:D87) -> 12952 | E88: =D88/$D$89 -> 0.13789139 | F88: =SUM(F86:F87) -> 8449 | G88: =F88/$F$89 -> 0.090986431 | H88: =(B88-D88)/D88 -> 0.93915998 | I88: =(D88-F88)/F88 -> 0.53296248
A89: Total du passif et des capitaux propres | B89: =B83+B88 -> 95806 | C89: =B89/$B$89 -> 1 | D89: =D83+D88 -> 93929 | E89: =D89/$D$89 -> 1 | F89: =F83+F88 -> 92860 | G89: =F89/$F$89 -> 1 | H89: =(B89-D89)/D89 -> 0.019983179 | I89: =(D89-F89)/F89 -> 0.011511953
A92: Note 1 : Immobilisations corporelles
A93: Solde d’ouverture | B93: =D96 -> 83129 | D93: =F96 -> 82200 | F93: 81500
A94: Acquisitions d’immobilisations | B94: 9887 | D94: 8579 | F94: 8000
A95: Amortissement | B95: =-B22 -> -8710 | D95: =-D22 -> -7650 | F95: =-F22 -> -7300
A96: Solde de clôture | B96: =SUM(B93:B95) -> 84306 | D96: =SUM(D93:D95) -> 83129 | F96: =SUM(F93:F95) -> 82200
A100: Waste Disposal Inc.
A101: État des flux de trésorerie
A102: pour les exercices clos les 31 décembre
A103: (en milliers de dollars canadiens)
B104: PROJET | D104: AUDITÉ
B105: 2020 | D105: 2019
B106: $ | D106: $
A107: Activités d’exploitation
A108: Bénéfice net | B108: =B34 -> 2164 | D108: =D34 -> 4503
A109: Éléments sans effet sur la trésorerie :
A110: Amortissement | B110: =-B95 -> 8710 | D110: =-D95 -> 7650
A111: Charge de désactualisation | B111: =B23 -> 140 | D111: =D23 -> 135
B112: =SUM(B110:B111) -> 8850 | D112: =SUM(D110:D111) -> 7785
A114: Variation des soldes du fonds de roulement
A115: Créances clients | B115: =D63-B63 -> -900 | D115: =F63-D63 -> -410
A116: Frais payés d’avance | B116: =D64-B64 -> -30 | D116: =F64-D64 -> -60
A117: Fournisseurs et charges à payer | B117: =B73-D73 -> 573 | D117: =D73-F73 -> 311
A118: Impôts à payer | B118: =B74-D74 -> -400 | D118: =D74-F74 -> -50
A119: Produits reportés | B119: =B75-D75 -> 100 | D119: =D75-F75 -> 170
B120: =SUM(B115:B119) -> -657 | D120: =SUM(D115:D119) -> -39
A122: Flux de trésorerie liés aux activités d’exploitation | B122: =B108+B112+B120 -> 10357 | D122: =D108+D112+D120 -> 12249 | F122: =(B122-D122)/D122 -> -0.15446159
...

Sheet résumé FF
A2: Forces | B2: 1 | C2: Installations à proximité
B3: 2 | C3: Intégration verticale
B4: 3 | C4: Contrats long terme/relation client
B5: 4 | C5: Stabilité et qualité de la MOD (salaires +)
B6: 5 | C6: Propriétaire de tous ses actifs
B7: 6 | C7: Bonne réputation
B8: 7 | C8: Clientèle cible en croissance
B9: 8 | C9: Expérience kingsley en redressement
B10: 9 | C10: CA efficace
B11: 10 | C11: Logiciel d'optimisation des parcours
A13: Faiblesses | B13: 11 | C13: Retard techno
B14: 12 | C14: Retard développement durable
B15: 13 | C15: Offre de service limitée
B16: 14 | C16: Site web non mis à jour et non informatif
B17: 15 | C17: Vision contradictoire des actionnaires
B18: 16 | C18: Difficulté à acquérir de nouveaux clients - Perte d'appel d'offre
B19: 17 | C19: GES plus élevés que l'indus
B20: 18 | C20: Petite taille donc moins d'économies d'échelles
B21: 19 | C21: 5% des camions utilisent le biogaz
B22: 20 | C22: Diminution des prix des matières recyclées à affecté la rentabilité de la division recyclage

Sheet Ratios
B6: Industrie de la gestion des déchets | F6: Données de référence
B10: 2020 | C10: 2019 | D10: 2018 | F10: Industrie
A11: Charges en pourcentage du total des produits
A12: Main-d’œuvre et avantages sociaux | B12: ='États financiers - Analyse'!B19/'États financiers - Analyse'!B16 -> 0.16921182 | C12: ='États financiers - Analyse'!D19/'États financiers - Analyse'!D16 -> 0.15108359 | D12: ='États financiers - Analyse'!F19/'États financiers - Analyse'!F16 -> 0.14511906 | F12: ='ANN IV – Données réf. sector.'!D8 -> 0.166
A13: Carburant et autres achats | B13: ='États financiers - Analyse'!B21/'États financiers - Analyse'!B16 -> 0.24285714 | C13: ='États financiers - Analyse'!D21/'États financiers - Analyse'!D16 -> 0.24396285 | D13: ='États financiers - Analyse'!F21/'États financiers - Analyse'!F16 -> 0.24560529 | F13: ='ANN IV – Données réf. sector.'!D9 -> 0.22
A14: Amortissement | B14: ='États financiers - Analyse'!B22/'États financiers - Analyse'!B16 -> 0.10726601 | C14: ='États financiers - Analyse'!D22/'États financiers - Analyse'!D16 -> 0.094736842 | D14: ='États financiers - Analyse'!F22/'États financiers - Analyse'!F16 -> 0.091011096 | F14: ='ANN IV – Données réf. sector.'!D10 -> 0.072
A15: Autres coûts d’exploitation | B15: ='États financiers - Analyse'!B24/'États financiers - Analyse'!B16 -> 0.24337438 | C15: ='États financiers - Analyse'!D24/'États financiers - Analyse'!D16 -> 0.22891641 | D15: ='États financiers - Analyse'!F24/'États financiers - Analyse'!F16 -> 0.22116943 | F15: ='ANN IV – Données réf. sector.'!D11 -> 0.262
A16: Frais de vente et d’administration | B16: ='États financiers - Analyse'!B25/'États financiers - Analyse'!B16 -> 0.10221675 | C16: ='États financiers - Analyse'!D25/'États financiers - Analyse'!D16 -> 0.099690402 | D16: ='États financiers - Analyse'!F25/'États financiers - Analyse'!F16 -> 0.098740805 | F16: ='ANN IV – Données réf. sector.'!D12 -> 0.1
A18: Marge du bénéfice d’exploitation | B18: =('États financiers - Analyse'!B28+'États financiers - Analyse'!B23)/'États financiers - Analyse'!B16 -> 0.082118227 | C18: =('États financiers - Analyse'!D28+'États financiers - Analyse'!D23)/'États financiers - Analyse'!D16 -> 0.13083591 | D18: =('États financiers - Analyse'!F28+'États financiers - Analyse'!F23)/'États financiers - Analyse'!F16 -> 0.14848523 | F18: ='ANN IV – Données réf. sector.'!D14 -> 0.1
A19: Rendement de l’actif | B19: ='États financiers - Analyse'!B34/'États financiers - Analyse'!B68 -> 0.022587312 | C19: ='États financiers - Analyse'!D34/'États financiers - Analyse'!D68 -> 0.047940466 | D19: ='États financiers - Analyse'!F34/'États financiers - Analyse'!F68 -> 0.057193625 | F19: ='ANN IV – Données réf. sector.'!D15 -> 0.09
A20: Rendement des capitaux propres | B20: ='États financiers - Analyse'!B34/'États financiers - Analyse'!B88 -> 0.086160217 | C20: ='États financiers - Analyse'!D34/'États financiers - Analyse'!D88 -> 0.34766831 | D20: ='États financiers - Analyse'!F34/'États financiers - Analyse'!F88 -> 0.6285951 | F20: ='ANN IV – Données réf. sector.'!D16 -> 0.08
A22: Ratio de liquidité générale | B22: ='États financiers - Analyse'!B65/'États financiers - Analyse'!B78 -> 0.81803955 | C22: ='États financiers - Analyse'!D65/'États financiers - Analyse'!D78 -> 0.52721504 | D22: ='États financiers - Analyse'!F65/'États financiers - Analyse'!F78 -> 0.88435374 | F22: ='ANN IV – Données réf. sector.'!D18 -> 1.5
A23: Délai de recouvrement des créances | B23: ='États financiers - Analyse'!B63/'États financiers - Analyse'!B16*365 -> 45.400246 | C23: ='États financiers - Analyse'!D63/'États financiers - Analyse'!D16*365 -> 41.585139 | D23: ='États financiers - Analyse'!F63/'États financiers - Analyse'!F16*365 -> 39.999377 | F23: ='ANN IV – Données réf. sector.'!D19 -> 45
A24: Dette à long terme/BAIIA | B24: =('États financiers - Analyse'!B80+'États financiers - Analyse'!B81+'États financiers - Analyse'!B82)/('États financiers - Analyse'!B28+'États financiers - Analyse'!B22+'États financiers - Analyse'!B23) -> 3.6826635 | C24: =('États financiers - Analyse'!D80+'États financiers - Analyse'!D81+'États financiers - Analyse'!D82)/('États financiers - Analyse'!D28+'États financiers - Analyse'!D22+'États financiers - Analyse'!D23) -> 3.3209992 | D24: =('États financiers - Analyse'!F80+'États financiers - Analyse'!F81+'États financiers - Analyse'!F82)/('États financiers - Analyse'!F28+'États financiers - Analyse'!F22+'États financiers - Analyse'!F23) -> 3.766632 | F24: ='ANN IV – Données réf. sector.'!D21 -> 3.1
A27: Clauses restrictives | G27: Contrainte
A28: BAII/intérêts | B28: =('États financiers - Analyse'!B28+'États financiers - Analyse'!B23)/-('États financiers - Analyse'!B29+'États financiers - Analyse'!B30+'États financiers - Analyse'!B31-'États financiers - Analyse'!B23) -> 1.7905478 | C28: =('États financiers - Analyse'!D28+'États financiers - Analyse'!D23)/-('États financiers - Analyse'!D29+'États financiers - Analyse'!D30+'États financiers - Analyse'!D31-'États financiers - Analyse'!D23) -> 2.3800405 | D28: =('États financiers - Analyse'!F28+'États financiers - Analyse'!F23)/-('États financiers - Analyse'!F29+'États financiers - Analyse'!F30+'États financiers - Analyse'!F31-'États financiers - Analyse'!F23) -> 2.5426985 | G28: >1,8
A29: Ratio emprunts/capitaux propres | B29: ='États financiers - Analyse'!B83/'États financiers - Analyse'!B88 -> 2.8145405 | C29: ='États financiers - Analyse'!D83/'États financiers - Analyse'!D88 -> 6.2520846 | D29: ='États financiers - Analyse'!F83/'États financiers - Analyse'!F88 -> 9.9906498 | F29: ='ANN IV – Données réf. sector.'!D20 -> 2.6 | G29: <3,5
A31: Secteur du recyclage
B33: 2020 WDI | F33: Industrie
A34: Charges en pourcentage du total des produits
A35: Main-d’œuvre et avantages sociaux | B35: ='ANN III – Info sectorielle'!F9/'ANN III – Info sectorielle'!F6 -> 0.23287671 | F35: ='ANN IV – Données réf. sector.'!D26 -> 0.212
A36: Coût des marchandises vendues | B36: ='ANN III – Info sectorielle'!F10/'ANN III – Info sectorielle'!F6 -> 0.5890411 | F36: ='ANN IV – Données réf. sector.'!D27 -> 0.541
A37: Amortissement | B37: ='ANN III – Info sectorielle'!F12/'ANN III – Info sectorielle'!F6 -> 0.05 | F37: ='ANN IV – Données réf. sector.'!D28 -> 0.059
A38: Autres coûts d’exploitation | B38: =('ANN III – Info sectorielle'!F11+'ANN III – Info sectorielle'!F13)/'ANN III – Info sectorielle'!F6 -> 0.11164384 | F38: ='ANN IV – Données réf. sector.'!D29 -> 0.125
A40: Marge du bénéfice d’exploitation | B40: ='ANN III – Info sectorielle'!F16/'ANN III – Info sectorielle'!F6 -> 0.016438356 | F40: ='ANN IV – Données réf. sector.'!D31 -> 0.043
A44: Variations des ventes annuelles par secteur | F44: Croissance annuelle | H44: Industrie
B45: 2020 | C45: 2019 | D45: 2018 | F45: 2020 | G45: 2019
B46: (en milliers de dollars canadiens)
A47: Collecte | B47: ='États financiers - Analyse'!B12 -> 48400 | C47: ='États financiers - Analyse'!D12 -> 47500 | D47: ='États financiers - Analyse'!F12 -> 46700 | F47: =(B47-C47)/C47 -> 0.018947368 | G47: =(C47-D47)/D47 -> 0.017130621 | H47: 0.02
A48: Transfert | B48: ='États financiers - Analyse'!B13 -> 8200 | C48: ='États financiers - Analyse'!D13 -> 8050 | D48: ='États financiers - Analyse'!F13 -> 7910 | F48: =(B48-C48)/C48 -> 0.01863354 | G48: =(C48-D48)/D48 -> 0.017699115 | H48: 0.02
A49: Enfouissement | B49: ='États financiers - Analyse'!B14 -> 17300 | C49: ='États financiers - Analyse'!D14 -> 16700 | D49: ='États financiers - Analyse'!F14 -> 16400 | F49: =(B49-C49)/C49 -> 0.035928144 | G49: =(C49-D49)/D49 -> 0.018292683 | H49: 0.02
A50: Recyclage | B50: ='États financiers - Analyse'!B15 -> 7300 | C50: ='États financiers - Analyse'!D15 -> 8500 | D50: ='États financiers - Analyse'!F15 -> 9200 | F50: =(B50-C50)/C50 -> -0.14117647 | G50: =(C50-D50)/D50 -> -0.076086957 | H50: -0.02
A51: Total | B51: =SUM(B47:B50) -> 81200 | C51: =SUM(C47:C50) -> 80750 | D51: =SUM(D47:D50) -> 80210 | F51: =(B51-C51)/C51 -> 0.0055727554 | G51: =(C51-D51)/D51 -> 0.0067323276
B54: Main-d’œuvre et avantages sociaux | C54: Pourcentage des ventes
B55: (en milliers de dollars canadiens)
A57: Collecte | B57: ='ANN III – Info sectorielle'!C9 -> 8670 | C57: =B57/'ANN III – Info sectorielle'!C6 -> 0.17913223
A58: Stations de transfert | B58: ='ANN III – Info sectorielle'!D9 -> 1270 | C58: =B58/'ANN III – Info sectorielle'!D6 -> 0.15487805
A59: Enfouissement | B59: ='ANN III – Info sectorielle'!E9 -> 2100 | C59: =B59/'ANN III – Info sectorielle'!E6 -> 0.12138728
A60: Recyclage | B60: ='ANN III – Info sectorielle'!F9 -> 1700 | C60: =B60/'ANN III – Info sectorielle'!F6 -> 0.23287671
