Workbook

Sheet Énoncé - acq
A1: Mère acquiert 100 % des actions avec droit de vote de Filiale le 1er janvier 2021 en contrepartie de :
B2: 200000 | C2: en trésorerie
B3: 100000 | C3: actions privilégiées émises par Mère, donnant droit à un dividende de 8 % cumulatif, rachetables le 1er janvier 2023
B4: ? | C4: 10 % du BAIIA excédent 500 000 $ pour les deux prochaines années
A5: De plus, le vendeur et ex-dirigeant de filiale a accepté d'être à l'emploi de Filiale pour la prochaine année en échange d'une rémunération de 150 000 $.
A8: Bilan de Filiale au 1er janvier 2021
C10: Valeur comptable | E10: Juste valeur
B11: ACTIF
B12: Court terme | M12: 300000
B13: Encaisse | C13: 15000
B14: Clients et autres débiteurs | C14: 30000 | E14: Provision insuffisante estimée à 4 000 $ | K14: -4000 | M14: EPC | N14: =+M12-C32 -> 118000
B15: Stocks | C15: 50000 | E15: Inclut des stocks pour une valeur de 3 000 $ qui datent de plus de trois ans | K15: -3000
B16: Frais payés d'avance | C16: 2000 | K16: -50000 | M16: Good will | N16: =+N14+K21 -> 118000
C17: =SUM(C13:C16) -> 97000 | K17: =36*2000 -> 72000 | N17: =+N16-K14-K15-K16-K17-K18 -> 123000
K18: -20000
B19: Immobilisations corporelles | C19: 350000 | E19: Hypothèse : équipement de production, amortissement dégressif 30 % ; juste valeur 300 000 $
C20: =SUM(C17:C19) -> 447000
B21: PASSIF
B22: Court terme
B23: Créditeurs | C23: 25000 | I23: PMT | J23: =-2000 -> -2000
B24: Portion courante de la dette à long terme | C24: 60000 | I24: FV | J24: 0
C25: =SUM(C23:C24) -> 85000 | I25: I | J25: =8%/12 -> 0.0066666667
I26: N | J26: 36
B27: DETTE À LONG TERME | C27: 180000 | I27: PV | J27: =PV(J25,J26,J23,J24,1) -> 64249.102
C28: =SUM(C25:C27) -> 265000
B29: CAPITAUX PROPRES
B30: Actions ordinaires | C30: 40000
B31: Bénéfices non répartis | C31: =+C32-C30 -> 142000
C32: =+C33-C28 -> 182000
C33: =+C20 -> 447000
A35: Filiale loue un espace à un prix de 10 000 $ / mois alors que le même espace coûterait 12 000 $ / mois lors de l'acquisition - il reste 36 mois au bail
A36: Filiale est poursuivie par un client pour une somme de 80 000 $, mais assure qu'il n'y a pas de cause. L'avocat de Mère a regardé le dossier et croit qu'il serait souhaitable de régler hors cours et croit pouvoir obtenir un règlement qui coûterait 20 000 $.
A37: Filiale prétend que le BAIIA des deux prochaines années atteindra 550 000 $ mais Mère croit plutôt qu'il s'élèvera à 450 000 $
A40: La méthode EF consolidée a été retenue. Calculer l'écart d'acquisition.

Sheet libre
A1: f

Sheet Solution
A2: 1 - Identification de l'acquéreur | E2: Mère
A4: 2 - Détermination de la date de l'acquisition | E4: 1er janvier 2021
N5: Calcul de l'écart d'acquisition
A6: 3 - Évaluation des éléments acquis et de toute participation ne donnant pas le contrôle
N7: Prix | O7: trésorerie | P7: 200000
C8: Valeur comptable | E8: Juste valeur | O8: JV act priv | P8: 100000 | R8: taux 8 % raisonnable, sinon aurait dû déterminer la JV de l'instrument financier
B9: ACTIF | O9: contrepartie conditionnelle | P9: 0 | Q9: =SUM(P7:P9) -> 300000 | R9: estimation de l'acquéreur retenue
B10: Court terme | R10: Rémunération 150 k$ à titre d'employé et non en contrepartie des actions vendues
B11: Encaisse | C11: 15000 | N11: Valeur comptable avoir act ord | Q11: =+C30 -> 182000
B12: Clients et autres débiteurs | C12: 30000 | E12: Provision insuffisante estimée à 4 000 $
B13: Stocks | C13: 50000 | E13: Inclut des stocks pour une valeur de 3 000 $ qui datent de plus de trois ans | Q13: =+Q9-Q11 -> 118000
B14: Frais payés d'avance | C14: 2000 | N14: Ajustements JV
C15: =SUM(C11:C14) -> 97000 | O15: Clients et autres débiteurs | P15: -4000 | Q15: 4000
O16: Stocks | P16: -3000 | Q16: 3000
B17: Immobilisations corporelles | C17: 350000 | E17: Hypothèse : équipement de production, amortissement dégressif 30 % ; juste valeur 300 000 $ | O17: Immobilisations corporelles | P17: -50000 | Q17: 50000
C18: =SUM(C15:C17) -> 447000 | O18: Contrat favorable - bail | P18: =-Q18 -> 64249.889 | Q18: =PV(8%/12,36,2000,1,1) -> -64249.889 | R18: actualisation de 2 000 $ pour une période de 36 mois, hypothèse taux 8 %
B19: PASSIF | O19: Poursuite | P19: 20000 | Q19: 20000
B20: Court terme | O20: Impôts futurs si ce choix de méthode comptable
B21: Créditeurs | C21: 25000 | N21: Écart d'acquisition | Q21: =SUM(Q13:Q19) -> 130750.11
B22: Portion courante de la dette à long terme | C22: 60000
C23: =SUM(C21:C22) -> 85000
B25: DETTE À LONG TERME | C25: 180000
C26: =SUM(C23:C25) -> 265000
B27: CAPITAUX PROPRES
B28: Actions ordinaires | C28: 40000
B29: Bénéfices non répartis | C29: =+C30-C28 -> 142000
C30: =+C31-C26 -> 182000
C31: =+C18 -> 447000
A33: Filiale loue un espace à un prix de 10 000 $ / mois alors que le même espace coûterait 12 000 $ / mois lors de l'acquisition - il reste 36 mois au bail
A34: Filiale est poursuivie par un client pour une somme de 80 000 $, mais assure qu'il n'y a pas de cause. L'avocat de Mère a regardé le dossier et croit qu'il serait souhaitable de régler hors cours et croit pouvoir obtenir un règlement qui coûterait 20 000 $.
A35: Filiale prétend que le BAIIA des deux prochaines années atteindra 550 000 $ mais Mère croit plutôt qu'il s'élèvera à 450 000 $

Sheet Énoncé 31 déc
A2: Les états financiers de Mère et Filiale au 31 décembre 2021 :
A3: Aucune transactions inter-sociétés
C6: Mère | E6: Filiale
B7: ACTIF
B8: Court terme
B9: Encaisse | C9: 100000 | E9: =E13-SUM(E10:E12) -> 173000
B10: Clients et autres débiteurs | C10: 340000 | E10: 29000
B11: Stocks | C11: 400000 | E11: 48000
B12: Frais payés d'avance | C12: 15000 | E12: 2000
C13: =SUM(C9:C12) -> 855000 | E13: =E17-E15 -> 252000
B15: Immobilisations corporelles | C15: 2000000 | E15: 360000
B16: Placement dans Filiale | C16: 300000
C17: =SUM(C13:C16) -> 3155000 | E17: =E31 -> 612000
B18: PASSIF
B19: Court terme
B20: Créditeurs | C20: 380000 | E20: 26000
B21: Portion courante de la dette à long terme | C21: 250000 | E21: 60000
C22: =SUM(C20:C21) -> 630000 | E22: =SUM(E20:E21) -> 86000
B24: DETTE À LONG TERME | C24: 1000000 | E24: 120000
C25: =SUM(C22:C24) -> 1630000 | E25: =SUM(E22:E24) -> 206000
B26: CAPITAUX PROPRES
B27: Actions ordinaires | C27: 300000 | E27: 40000
B28: Actions privilégiées | C28: 100000
B29: Bénéfices non répartis | C29: =+C30-C27-C28 -> 1125000 | E29: =+'Énoncé - acq'!C31+E41 -> 366000
C30: =+C31-C25 -> 1525000 | E30: =SUM(E27:E29) -> 406000
C31: =+C17 -> 3155000 | E31: =+E30+E25 -> 612000
B34: Ventes | C34: 4000000 | E34: 800000
B35: Coût des ventes | C35: 2100000 | E35: 300000
B36: Bénéfice brut | C36: =C34-C35 -> 1900000 | E36: =E34-E35 -> 500000
B38: Frais d'exploitation | C38: 1200000 | E38: 220000
B39: Bénéfice avant impôts | C39: =C36-C38 -> 700000 | E39: =E36-E38 -> 280000
B40: Impôts | C40: =+C39*0.2 -> 140000 | E40: =0.2*E39 -> 56000
B41: Bénéfice net | C41: =C39-C40 -> 560000 | E41: =E39-E40 -> 224000
B44: BAIIA | E44: =+E41+20000+110000 -> 354000
A46: Préparez les états financiers consolidés

Sheet libre 2

Sheet Solution 31 déc
C3: Mère | E3: Filiale | G3: Ajustements conso | K3: Consolidé
B4: ACTIF
B5: Court terme
B6: Encaisse | C6: 100000 | E6: =E10-SUM(E7:E9) -> 296000 | K6: =SUM(C6:H6) -> 396000
B7: Clients et autres débiteurs | C7: 340000 | E7: 29000 | G7: =+Solution!P15 -> -4000 | H7: =-G7 -> 4000 | K7: =SUM(C7:H7) -> 369000
B8: Stocks | C8: 400000 | E8: 48000 | G8: =+Solution!P16 -> -3000 | H8: =-G8 -> 3000 | K8: =SUM(C8:H8) -> 448000
B9: Frais payés d'avance | C9: 15000 | E9: 2000 | K9: =SUM(C9:H9) -> 17000
C10: =SUM(C6:C9) -> 855000 | E10: =E16-E12 -> 375000 | K10: =SUM(K6:K9) -> 1230000
B12: Immobilisations corporelles | C12: 2000000 | E12: 360000 | G12: =+Solution!P17 -> -50000 | H12: =-G12*0.3 -> 15000 | K12: =SUM(C12:H12) -> 2325000
B13: Placement dans Filiale | C13: 300000 | G13: =-C13 -> -300000 | K13: =SUM(C13:H13) -> 0
B14: Contrat bail favorable | G14: =+Solution!P18 -> 64249.889 | H14: =-(G14+I14) -> -19733.142 | I14: =PV(8%/12,24,2000,1,1) -> -44516.747 | K14: =SUM(C14:H14) -> 44516.747
B15: Écart d'acquisition | G15: =+Solution!Q21 -> 130750.11 | K15: =SUM(C15:H15) -> 130750.11
C16: =SUM(C10:C13) -> 3155000 | E16: =E32 -> 735000 | G16: =SUM(G6:G15) -> -162000 | H16: =SUM(H6:H15) -> 2266.858 | K16: =SUM(K10:K15) -> 3730266.9
B17: PASSIF | K17: =SUM(C17:H17) -> 0
B18: Court terme | K18: =SUM(C18:H18) -> 0
B19: Créditeurs | C19: 380000 | E19: 26000 | K19: =SUM(C19:H19) -> 406000
B20: Provision - poursuite | G20: =+Solution!P19 -> 20000 | K20: =SUM(C20:H20) -> 20000
B21: Portion courante de la dette à long terme | C21: 250000 | E21: 60000 | K21: =SUM(C21:H21) -> 310000
C22: =SUM(C19:C21) -> 630000 | E22: =SUM(E19:E21) -> 86000 | K22: =SUM(K19:K21) -> 736000
B24: DETTE À LONG TERME | C24: 1000000 | E24: 120000 | K24: =SUM(C24:H24) -> 1120000
B25: Actions privilégiées | G25: 100000 | I25: reclassement | K25: =SUM(C25:H25) -> 100000
C26: =SUM(C22:C24) -> 1630000 | E26: =SUM(E22:E24) -> 206000 | K26: =SUM(K22:K25) -> 1956000
B27: CAPITAUX PROPRES
B28: Actions ordinaires | C28: 300000 | E28: 40000 | G28: =-Solution!C28 -> -40000 | K28: =SUM(C28:H28) -> 300000
B29: Actions privilégiées | C29: 100000 | G29: -100000 | I29: reclassement | K29: =SUM(C29:H29) -> 0
B30: Bénéfices non répartis | C30: =+C31-C28-C29 -> 1125000 | E30: =+'Énoncé - acq'!C28+E42 -> 489000 | G30: =-Solution!C29 -> -142000 | H30: =+H7+H8+H12+H14 -> 2266.858 | K30: =SUM(C30:H30) -> 1474266.9
C31: =+C32-C26 -> 1525000 | E31: =SUM(E28:E30) -> 529000 | K31: =SUM(K28:K30) -> 1774266.9
C32: =+C16 -> 3155000 | E32: =+E31+E26 -> 735000 | G32: =SUM(G18:G31) -> -162000 | H32: =SUM(H18:H31) -> 2266.858 | K32: =+K31+K26 -> 3730266.9
K33: =SUM(C33:H33) -> 0
K34: =SUM(C34:H34) -> 0
B35: Ventes | C35: 4000000 | E35: 800000 | K35: =SUM(C35:H35) -> 4800000
B36: Coût des ventes | C36: 2100000 | E36: 300000 | K36: =SUM(C36:H36) -> 2400000
B37: Bénéfice brut | C37: =C35-C36 -> 1900000 | E37: =E35-E36 -> 500000 | K37: =K35-K36 -> 2400000
B39: Frais d'exploitation | C39: 1200000 | E39: 220000 | K39: =SUM(C39:H39) -> 1420000
B40: Bénéfice avant impôts | C40: =C37-C39 -> 700000 | E40: =E37-E39 -> 280000 | K40: =K37-K39 -> 980000
B41: Impôts | C41: =+C40*0.2 -> 140000 | E41: =0.2*E40 -> 56000 | K41: =SUM(C41:H41) -> 196000
B42: Bénéfice net | C42: =C40-C41 -> 560000 | E42: =E40-E41 -> 224000 | K42: =K40-K41 -> 784000
B45: BAIIA | E45: =+E42+20000+110000 -> 354000 | K45: si ajustement pour la contrepartie conditionnelle : au résultat net après 12 mois

Sheet Si acquiert 70 %
A2: Mère acquiert 70 % des actions avec droit de vote de Filiale le 1er janvier 2021 en contrepartie de :
B3: 200000 | C3: en trésorerie
A5: Bilan de Filiale au 1er janvier 2021
C7: Valeur comptable
B8: ACTIF
B9: Court terme
B10: Encaisse | C10: 15000
B11: Clients et autres débiteurs | C11: 30000 | E11: Provision insuffisante estimée à 4 000 $
B12: Stocks | C12: 50000 | E12: Inclut des stocks pour une valeur de 3 000 $ qui datent de plus de trois ans
B13: Frais payés d'avance | C13: 2000
C14: =SUM(C10:C13) -> 97000
B16: Immobilisations corporelles | C16: 350000 | E16: Hypothèse : équipement de production, amortissement dégressif 30 % ; juste valeur 300 000 $
C17: =SUM(C14:C16) -> 447000
B18: PASSIF
B19: Court terme
B20: Créditeurs | C20: 25000
B21: Portion courante de la dette à long terme | C21: 60000
C22: =SUM(C20:C21) -> 85000
B24: DETTE À LONG TERME | C24: 180000
C25: =SUM(C22:C24) -> 265000
B26: CAPITAUX PROPRES
B27: Actions ordinaires | C27: 40000
B28: Bénéfices non répartis | C28: =+C29-C27 -> 142000
C29: =+C30-C25 -> 182000
C30: =+C17 -> 447000
A33: La méthode EF consolidée a été retenue. Calculer l'écart d'acquisition.

Sheet libre 3

Sheet Solution 70 %
A3: Mère acquiert 70 % des actions avec droit de vote de Filiale le 1er janvier 2021 en contrepartie de :
B4: 200000 | C4: en trésorerie
M5: Calcul de l'écart d'acquisition | P5: 1
A6: Bilan de Filiale au 1er janvier 2021
M7: Prix | N7: trésorerie | O7: 200000 | P7: =+O7/0.7 -> 285714.29 | Q7: extrapolation du prix payé à 100 % des actions
C8: Valeur comptable
B9: ACTIF | M9: Valeur comptable avoir act ord | P9: =+C30 -> 182000
B10: Court terme
B11: Encaisse | C11: 15000 | P11: =P7-P9 -> 103714.29
B12: Clients et autres débiteurs | C12: 30000 | E12: Provision insuffisante estimée à 4 000 $
B13: Stocks | C13: 50000 | E13: Inclut des stocks pour une valeur de 3 000 $ qui datent de plus de trois ans | M13: Ajustements JV | Q13: à 100 %
B14: Frais payés d'avance | C14: 2000 | N14: Clients et autres débiteurs | O14: -4000 | P14: 4000
C15: =SUM(C11:C14) -> 97000 | N15: Stocks | O15: -3000 | P15: 3000
N16: Immobilisations corporelles | O16: -50000 | P16: 50000
B17: Immobilisations corporelles | C17: 350000 | E17: Hypothèse : équipement de production, amortissement dégressif 30 % ; juste valeur 300 000 $ | N17: Impôts futurs si ce choix de méthode comptable
C18: =SUM(C15:C17) -> 447000 | M18: Écart d'acquisition | P18: =SUM(P10:P17) -> 160714.29 | Q18: Choix | R18: =+P18 -> 160714.29
B19: PASSIF | R19: =+R18*0.7 -> 112500 | S19: réduction correspondate Part des actionnaires sans contrôle
B20: Court terme | M20: Part des actionnaires sans contrôle | P20: =+P7*0.3 -> 85714.286 | Q20: Présenté dans les capitaux propres
B21: Créditeurs | C21: 25000
B22: Portion courante de la dette à long terme | C22: 60000
C23: =SUM(C21:C22) -> 85000
B25: DETTE À LONG TERME | C25: 180000
C26: =SUM(C23:C25) -> 265000
B27: CAPITAUX PROPRES
B28: Actions ordinaires | C28: 40000
B29: Bénéfices non répartis | C29: =+C30-C28 -> 142000
C30: =+C31-C26 -> 182000
C31: =+C18 -> 447000
