Workbook

Sheet énoncé
A1: Résultat par action
A4: Bénéfice avant impôts | D4: 130000
A5: Bénéfice net | D5: 100000
A7: Actions en circulation | D7: 10000
A9: Débenture A | D9: 500000
A10: intérêts payable annuellement le 31 mars | D10: 0.08
A11: convertible par tranche de | D11: 1000
B12: en actions ordinaires | D12: 10
A14: Débenture B | D14: 200000
D15: 0.1
A16: émise le | C16: 43373
A17: convertible par tranche de | D17: 1000
B18: en actions ordinaires | D18: 15
A20: Actions préférentielles | D20: 3000
A21: pour une valeur de | D21: 300000
A22: rachetables au gré du détenteur
A23: dividende cumulatif | D23: 0.1
B24: non déclaré 2017 + 2018
A25: convertibles en actions ordinaires | D25: 1:1
A27: Options | D27: 250
A28: prix d'exercice | C28: 2019 | D28: 90
C29: 2020 | D29: 95
A31: Cous de l'action de la société
C32: moyen | D32: 100
C33: au 31 décembre | D33: 85
A35: Taux d'impôt | D35: 0.3
A38: Travail à faire :
A39: Calculez les résultats par action requis selon IAS 33 (IFRS)

Sheet solution
A2: Résultat de base
A4: Bénéfice net | C4: =+énoncé!D5 -> 100000 | D4: =+C4/C5 -> 10 | F4: et non BAI
A5: # actions ord | C5: =+énoncé!D7 -> 10000 | F5: Aucun ajust pour act préf car "dette" et donc coût déjà inclus dans résultat net
F6: uniquement act ord (et non act préf)
A8: Résultat dilué
A10: Débenture A
A11: =+énoncé!D9 -> 500000 | B11: =+énoncé!D10 -> 0.08 | C11: =+(1-énoncé!D35) -> 0.7 | E11: =+(A11*B11*C11) -> 28000 | F11: =+E11/E12 -> 5.6 | H11: date de paiement d'intérêts n'a pas d'impact sur charge de la période
A12: =+énoncé!D9/énoncé!D11 -> 500 | B12: =+énoncé!D12 -> 10 | E12: =+A12*B12 -> 5000
A14: Débenture B
A15: =+énoncé!D14 -> 200000 | B15: =+énoncé!D15 -> 0.1 | C15: =+(1-énoncé!D35) -> 0.7 | D15: =3/12 -> 0.25 | E15: =+(A15*B15*C15*D15) -> 3500 | F15: =+E15/E16 -> 4.6666667 | H15: émises le 30 sept de l'exercice en cours, donc 3 mois sur 12
A16: =+énoncé!D14/énoncé!D17 -> 200 | B16: =+énoncé!D18 -> 15 | D16: =3/12 -> 0.25 | E16: =+A16*B16*D16 -> 750
A18: Actions préférentielles
A19: =+énoncé!D21 -> 300000 | B19: =+énoncé!D23 -> 0.1 | E19: =+(A19*B19) -> 30000 | F19: =+E19/E20 -> 10 | H19: uniquement coût de l'exercice (et non l'arrérage)
A20: =+énoncé!D20 -> 3000 | B20: 1 | E20: =+A20*B20 -> 3000
A22: Options
A23: =+énoncé!D27 -> 250 | B23: =+énoncé!D28 -> 90 | C23: =+A23*B23 -> 22500 | H23: prendre le prix d'exercice le plus dilutif
A24: =+C23 -> 22500 | B24: =+énoncé!D32 -> 100 | C24: =+A24/B24 -> 225 | E24: 0 | F24: =+E24/E25 -> 0
A25: =+A23 -> 250 | B25: =+C24 -> 225 | E25: =+A25-B25 -> 25 | H25: émission moins rachat
D27: Bénéfice | F27: # actions
A29: Résultat de base | D29: =+C4 -> 100000 | F29: =+C5 -> 10000 | H29: =+D29/F29 -> 10
A30: options | D30: =+E24 -> 0 | F30: =+E25 -> 25 | J30: commencer avec le plus dilutif
D31: =SUM(D29:D30) -> 100000 | F31: =SUM(F29:F30) -> 10025 | H31: =+D31/F31 -> 9.9750623
A32: =+A14 -> Débenture B | D32: =+E15 -> 3500 | F32: =+E16 -> 750
D33: =SUM(D31:D32) -> 103500 | F33: =SUM(F31:F32) -> 10775 | H33: =+D33/F33 -> 9.6055684
A34: =+A10 -> Débenture A | D34: =+E11 -> 28000 | F34: =+E12 -> 5000
D35: =SUM(D33:D34) -> 131500 | F35: =SUM(F33:F34) -> 15775 | H35: =+D35/F35 -> 8.3359746
A37: Actions préférentielles non considérées car anti-dilutives

Sheet Sheet3
